ai_logic/__init__.py
ai_logic/doc_example.py
ai_logic/documentor_chat.py
doc_ignore/__init__.py
doc_ignore/doc_ignore.py
doc_log/__init__.py
doc_log/doc_log.py
doc_writer/__init__.py
doc_writer/doc_writer.py
documentation_orchestrator/__init__.py
documentation_orchestrator/added_files_manager.py
documentation_orchestrator/documentation_manager.py
documentation_orchestrator/first_run_manager.py
documentation_orchestrator/modified_files_manager.py
file_handler/__init__.py
file_handler/file_handler.py
git_tools/__init__.py
git_tools/git_file_checker.py
git_tools/git_file_paths.py
git_tools/git_manager.py
git_tools/git_retrieaver.py
metaclasses/__init__.py
metaclasses/no_instanciable_meta.py
metaclasses/singleton_meta.py
repository_scrapping/__init__.py
repository_scrapping/code_scrapper.py
repository_scrapping/file_scrapper.py
snippet_management/__init__.py
snippet_management/code_snippet.py
snippet_management/dependencies_info.py
snippet_management/node_info.py
snippet_management/snippet_extract.py
snippet_management/snippet_storage.py
tree_sitter_logic/__init__.py
tree_sitter_logic/languages.py
tree_sitter_logic/tree_sitter_util.py
documentorpp-0.3.dist-info/METADATA
documentorpp-0.3.dist-info/WHEEL
documentorpp-0.3.dist-info/entry_points.txt
documentorpp-0.3.dist-info/top_level.txt
documentorpp-0.3.dist-info/RECORD
