Metadata-Version: 2.1
Name: documentorpp
Version: 0.3
Requires-Dist: tree-sitter
Requires-Dist: pygit2
Requires-Dist: langchain
Requires-Dist: openai
Requires-Dist: wheel
